{
    "DOCTYPE": "PROP_SHEET",
    "props": [{
        "name": "plant1",
        "size": {
            "x": 16,
            "y": 16,
            "z": 56
        },
        "collType": "BLOCK",
        "fix": {
            "gfx": "media/map/twilight-interior.png",
            "x": 456,
            "y": 208,
            "w": 56,
            "h": 72,
            "flipX": false,
            "shape": "Y_FLAT"
        }
    }, {
        "name": "plant2",
        "size": {
            "x": 16,
            "y": 16,
            "z": 64
        },
        "collType": "BLOCK",
        "fix": {
            "gfx": "media/map/twilight-interior.png",
            "x": 480,
            "y": 280,
            "w": 32,
            "h": 80,
            "flipX": false,
            "shape": "Y_FLAT"
        }
    }, {
        "name": "plant3",
        "size": {
            "x": 16,
            "y": 16,
            "z": 32
        },
        "collType": "BLOCK",
        "fix": {
            "gfx": "media/map/twilight-interior.png",
            "x": 456,
            "y": 280,
            "w": 24,
            "h": 48,
            "flipX": false,
            "shape": "Y_FLAT"
        }
    }, {
        "name": "plant4",
        "size": {
            "x": 16,
            "y": 16,
            "z": 16
        },
        "collType": "BLOCK",
        "fix": {
            "gfx": "media/map/twilight-interior.png",
            "x": 464,
            "y": 360,
            "w": 16,
            "h": 32,
            "flipX": false,
            "shape": "Y_FLAT"
        }
    }, {
        "name": "plant5",
        "size": {
            "x": 16,
            "y": 16,
            "z": 16
        },
        "collType": "BLOCK",
        "fix": {
            "gfx": "media/map/twilight-interior.png",
            "x": 480,
            "y": 360,
            "w": 16,
            "h": 32,
            "flipX": false,
            "shape": "Y_FLAT"
        }
    }, {
        "name": "plant6",
        "size": {
            "x": 16,
            "y": 16,
            "z": 16
        },
        "collType": "BLOCK",
        "fix": {
            "gfx": "media/map/twilight-interior.png",
            "x": 496,
            "y": 360,
            "w": 16,
            "h": 32,
            "flipX": false,
            "shape": "Y_FLAT"
        }
    }, {
        "name": "terminalN",
        "size": {
            "x": 32,
            "y": 12,
            "z": 12
        },
        "collType": "BLOCK",
        "fix": {
            "gfx": "media/map/twilight-interior.png",
            "x": 384,
            "y": 240,
            "w": 32,
            "h": 24,
            "flipX": false
        }
    }, {
        "name": "terminalE",
        "size": {
            "x": 12,
            "y": 32,
            "z": 12
        },
        "collType": "BLOCK",
        "fix": {
            "gfx": "media/map/twilight-interior.png",
            "x": 404,
            "y": 264,
            "w": 12,
            "h": 40,
            "flipX": false
        }
    }, {
        "name": "terminalW",
        "size": {
            "x": 12,
            "y": 32,
            "z": 12
        },
        "collType": "BLOCK",
        "fix": {
            "gfx": "media/map/twilight-interior.png",
            "x": 404,
            "y": 264,
            "w": 12,
            "h": 40,
            "flipX": true
        }
    }, {
        "name": "shelfE",
        "size": {
            "x": 12,
            "y": 32,
            "z": 40
        },
        "collType": "BLOCK",
        "fix": {
            "gfx": "media/map/twilight-interior.png",
            "x": 128,
            "y": 248,
            "w": 12,
            "h": 72,
            "flipX": true
        }
    }, {
        "name": "shelfW",
        "size": {
            "x": 12,
            "y": 32,
            "z": 40
        },
        "collType": "BLOCK",
        "fix": {
            "gfx": "media/map/twilight-interior.png",
            "x": 128,
            "y": 248,
            "w": 12,
            "h": 72,
            "flipX": false
        }
    }, {
        "name": "picture",
        "size": {
            "x": 24,
            "y": 4,
            "z": 16
        },
        "collType": "NONE",
        "anims": {
            "sheet": {
                "src": "media/map/twilight-interior.png",
                "width": 24,
                "height": 16,
                "offX": 432,
                "offY": 208,
                "xCount": 1
            },
            "SUB": [{
                "name": "croissant",
                "time": 0.1,
                "frames": [0],
                "repeat": true
            }, {
                "name": "autumn",
                "time": 0.1,
                "frames": [1],
                "repeat": true
            }, {
                "name": "bergen",
                "time": 0.1,
                "frames": [2],
                "repeat": true
            }, {
                "name": "fajro",
                "time": 0.1,
                "frames": [3],
                "repeat": true
            }, {
                "name": "maroon",
                "time": 0.1,
                "frames": [4],
                "repeat": true
            }]
        }
    }, {
        "name": "chair-down",
        "size": {
            "x": 12,
            "y": 12,
            "z": 20
        },
        "collType": "BLOCK",
        "fix": {
            "gfx": "media/map/twilight-interior.png",
            "x": 128,
            "y": 208,
            "w": 16,
            "h": 32,
            "flipX": false,
            "wallY": 1
        }
    }, {
        "name": "chair-right",
        "size": {
            "x": 12,
            "y": 12,
            "z": 20
        },
        "collType": "BLOCK",
        "fix": {
            "gfx": "media/map/twilight-interior.png",
            "x": 144,
            "y": 208,
            "w": 16,
            "h": 32,
            "flipX": false,
            "wallY": 1
        }
    }, {
        "name": "chair-left",
        "size": {
            "x": 12,
            "y": 12,
            "z": 20
        },
        "collType": "BLOCK",
        "fix": {
            "gfx": "media/map/twilight-interior.png",
            "x": 144,
            "y": 208,
            "w": 16,
            "h": 32,
            "flipX": true,
            "wallY": 1
        }
    }, {
        "name": "chair-up",
        "size": {
            "x": 12,
            "y": 12,
            "z": 20
        },
        "collType": "BLOCK",
        "fix": {
            "gfx": "media/map/twilight-interior.png",
            "x": 160,
            "y": 208,
            "w": 16,
            "h": 32,
            "flipX": false,
            "wallY": 0
        }
    }, {
        "name": "umbrella1",
        "size": {
            "x": 12,
            "y": 12,
            "z": 20
        },
        "collType": "VIRTUAL",
        "fix": {
            "gfx": "media/map/twilight-interior.png",
            "x": 144,
            "y": 368,
            "w": 16,
            "h": 32,
            "flipX": false,
            "wallY": 0
        }
    }, {
        "name": "umbrella2",
        "size": {
            "x": 12,
            "y": 12,
            "z": 20
        },
        "collType": "VIRTUAL",
        "fix": {
            "gfx": "media/map/twilight-interior.png",
            "x": 160,
            "y": 368,
            "w": 16,
            "h": 32,
            "flipX": false,
            "wallY": 0
        }
    }, {
        "name": "umbrella3",
        "size": {
            "x": 12,
            "y": 12,
            "z": 20
        },
        "collType": "VIRTUAL",
        "fix": {
            "gfx": "media/map/twilight-interior.png",
            "x": 176,
            "y": 368,
            "w": 16,
            "h": 32,
            "flipX": false,
            "wallY": 0
        }
    }, {
        "name": "umbrella4",
        "size": {
            "x": 12,
            "y": 12,
            "z": 20
        },
        "collType": "VIRTUAL",
        "fix": {
            "gfx": "media/map/twilight-interior.png",
            "x": 144,
            "y": 400,
            "w": 16,
            "h": 32,
            "flipX": false,
            "wallY": 0
        }
    }, {
        "name": "umbrella5",
        "size": {
            "x": 12,
            "y": 12,
            "z": 20
        },
        "collType": "VIRTUAL",
        "fix": {
            "gfx": "media/map/twilight-interior.png",
            "x": 160,
            "y": 400,
            "w": 16,
            "h": 32,
            "flipX": false,
            "wallY": 0
        }
    }, {
        "name": "laserboard1",
        "size": {
            "x": 32,
            "y": 8,
            "z": 40
        },
        "collType": "VIRTUAL",
        "fix": {
            "gfx": "media/map/twilight-interior.png",
            "x": 400,
            "y": 304,
            "w": 32,
            "h": 48,
            "flipX": false,
            "wallY": 0
        }
    }, {
        "name": "laserboard2",
        "size": {
            "x": 32,
            "y": 8,
            "z": 40
        },
        "collType": "VIRTUAL",
        "fix": {
            "gfx": "media/map/twilight-interior.png",
            "x": 400,
            "y": 352,
            "w": 32,
            "h": 48,
            "flipX": false,
            "wallY": 0
        }
    }, {
        "name": "laserboard3",
        "size": {
            "x": 32,
            "y": 8,
            "z": 40
        },
        "collType": "VIRTUAL",
        "fix": {
            "gfx": "media/map/twilight-interior.png",
            "x": 400,
            "y": 304,
            "w": 32,
            "h": 48,
            "flipX": true,
            "wallY": 0
        }
    }, {
        "name": "drything1",
        "size": {
            "x": 32,
            "y": 12,
            "z": 20
        },
        "collType": "BLOCK",
        "fix": {
            "gfx": "media/map/twilight-interior.png",
            "x": 176,
            "y": 400,
            "w": 32,
            "h": 32,
            "flipX": false,
            "wallY": 0
        }
    }, {
        "name": "drything2",
        "size": {
            "x": 32,
            "y": 12,
            "z": 20
        },
        "collType": "BLOCK",
        "fix": {
            "gfx": "media/map/twilight-interior.png",
            "x": 208,
            "y": 400,
            "w": 32,
            "h": 32,
            "flipX": false,
            "wallY": 0
        }
    }, {
        "name": "drything3",
        "size": {
            "x": 16,
            "y": 12,
            "z": 20
        },
        "collType": "BLOCK",
        "fix": {
            "gfx": "media/map/twilight-interior.png",
            "x": 240,
            "y": 400,
            "w": 16,
            "h": 32,
            "flipX": false,
            "wallY": 0
        }
    }, {
        "name": "drything4",
        "size": {
            "x": 16,
            "y": 12,
            "z": 20
        },
        "collType": "BLOCK",
        "fix": {
            "gfx": "media/map/twilight-interior.png",
            "x": 256,
            "y": 400,
            "w": 16,
            "h": 32,
            "flipX": false,
            "wallY": 0
        }
    }, {
        "name": "drythingDiag1",
        "size": {
            "x": 24,
            "y": 24,
            "z": 24
        },
        "collType": "BLOCK",
        "shapeType": "SLOPE_SE",
        "fix": {
            "gfx": "media/map/twilight-interior.png",
            "x": 144,
            "y": 432,
            "w": 24,
            "h": 48,
            "flipX": false,
            "wallY": 1
        }
    }, {
        "name": "drythingDiag2",
        "size": {
            "x": 24,
            "y": 24,
            "z": 24
        },
        "collType": "BLOCK",
        "shapeType": "SLOPE_SW",
        "fix": {
            "gfx": "media/map/twilight-interior.png",
            "x": 144,
            "y": 432,
            "w": 24,
            "h": 48,
            "flipX": true,
            "wallY": 1
        }
    }, {
        "name": "smalltable1",
        "size": {
            "x": 16,
            "y": 16,
            "z": 8
        },
        "collType": "BLOCK",
        "fix": {
            "gfx": "media/map/twilight-interior.png",
            "x": 480,
            "y": 160,
            "w": 16,
            "h": 21,
            "flipX": true,
            "wallY": 1
        }
    }, {
        "name": "smalltable2",
        "size": {
            "x": 16,
            "y": 16,
            "z": 8
        },
        "collType": "BLOCK",
        "fix": {
            "gfx": "media/map/twilight-interior.png",
            "x": 480,
            "y": 184,
            "w": 16,
            "h": 21,
            "flipX": true,
            "wallY": 1
        }
    }, {
        "name": "lamp1",
        "size": {
            "x": 16,
            "y": 16,
            "z": 40
        },
        "collType": "BLOCK",
        "fix": {
            "gfx": "media/map/twilight-interior.png",
            "x": 160,
            "y": 280,
            "w": 16,
            "h": 56,
            "flipX": false,
            "shape": "Y_FLAT"
        }
    }]
}